resource/Minecraft_missing_texture_block.svg.png
t3dlitematica/__init__.py
t3dlitematica/__main__.py
t3dlitematica/litematicadecoder/LitematicaHandler.py
t3dlitematica/litematicadecoder/NBTHandler.py
t3dlitematica/litematicadecoder/Utilities.py
t3dlitematica/litematicadecoder/__init__.py
t3dlitematica/litematicadecoder/bitstack.py
t3dlitematica/objbuilder/__init__.py
t3dlitematica/objbuilder/mctoobj.py
t3dlitematica/objbuilder/toobj.py
t3dlitematica/texturepackexport/__init__.py
t3dlitematica/texturepackexport/convert.py
t3dlitematica/texturepackexport/multiload.py
3dLitematica-0.3.4.dist-info/LICENSE
3dLitematica-0.3.4.dist-info/METADATA
3dLitematica-0.3.4.dist-info/WHEEL
3dLitematica-0.3.4.dist-info/entry_points.txt
3dLitematica-0.3.4.dist-info/top_level.txt
3dLitematica-0.3.4.dist-info/RECORD
