Metadata-Version: 2.1
Name: 3dLitematica
Version: 0.3.4
Summary: A tool can transform Litematica to 3D Obj
Author: LegendsOfSky
Author-email: phillychi3 <phillychi3@gmail.com>
License: GNU GENERAL PUBLIC LICENSE
Project-URL: Repository, https://github.com/MCRTD/3Dlitematica.git
Keywords: minecraft,Litematica
Classifier: Programming Language :: Python :: 3
Requires-Python: >=3.8
License-File: LICENSE
Requires-Dist: alive-progress
Requires-Dist: click
